itomate/__init__.py
itomate/itomate.py
itomate2-0.4.2.dist-info/METADATA
itomate2-0.4.2.dist-info/WHEEL
itomate2-0.4.2.dist-info/entry_points.txt
itomate2-0.4.2.dist-info/top_level.txt
itomate2-0.4.2.dist-info/RECORD
