Metadata-Version: 2.4
Name: itomate2
Version: 0.4.2
Summary: Automate your iTerm layouts and workflows
Home-page: https://github.com/melefabrizio/itomate
Author: Fabrizio Mele
Author-email: fabrizio@mele.io
License: MIT
Classifier: Programming Language :: Python :: 3
Classifier: License :: OSI Approved :: MIT License
Classifier: Operating System :: MacOS
Requires-Python: >=3.7.0
Requires-Dist: iterm2>=1.1
Requires-Dist: PyYAML>=5.3.1
Dynamic: author
Dynamic: author-email
Dynamic: classifier
Dynamic: description
Dynamic: description-content-type
Dynamic: home-page
Dynamic: license
Dynamic: requires-dist
Dynamic: requires-python
Dynamic: summary
